plant_pathology/__init__.py
plant_pathology/_nbdev.py
plant_pathology/all.py
plant_pathology/config.py
plant_pathology/create_folds.py
plant_pathology/dataset.py
plant_pathology/evaluate.py
plant_pathology/generate_pseudo_labels.py
plant_pathology/pretrained_models.py
plant_pathology/self_knowledge_distillation.py
plant_pathology/train.py
plant_pathology/utils.py
plant_pathology-0.0.3.dist-info/LICENSE
plant_pathology-0.0.3.dist-info/METADATA
plant_pathology-0.0.3.dist-info/WHEEL
plant_pathology-0.0.3.dist-info/entry_points.txt
plant_pathology-0.0.3.dist-info/top_level.txt
plant_pathology-0.0.3.dist-info/RECORD
