Metadata-Version: 2.1
Name: plant-pathology
Version: 0.0.3
Summary: My submission the (completed) Plant Pathology 2020 competition on Kaggle.
Home-page: https://github.com/bwolfson97/plant_pathology/tree/master/
Author: Brandon Wolfson
Author-email: bwolfson97@gmail.com
License: Apache Software License 2.0
Keywords: plant pathology kaggle leaves deep learning AI
Platform: UNKNOWN
Classifier: Development Status :: 3 - Alpha
Classifier: Intended Audience :: Developers
Classifier: License :: OSI Approved :: Apache Software License
Classifier: Natural Language :: English
Classifier: Programming Language :: Python :: 3.6
Classifier: Programming Language :: Python :: 3.7
Classifier: Programming Language :: Python :: 3.8
Requires-Python: >=3.6
Requires-Dist: fastcore
Requires-Dist: fastai
Requires-Dist: wwf
Requires-Dist: timm
Requires-Dist: wandb
Requires-Dist: numpy
